Metadata-Version: 2.1
Name: PhotoDB
Version: 0.1.4
Summary: App for cataloguing vintage cameras, lenses, films, negatives & prints
Home-page: https://github.com/djjudas21/photodb
Author: Jonathan Gazeley
Author-email: photodb@jonathangazeley.com
License: MIT
Platform: UNKNOWN
Classifier: Development Status :: 4 - Beta
Classifier: Environment :: Other Environment
Classifier: Operating System :: MacOS :: MacOS X
Classifier: Operating System :: POSIX
Classifier: Programming Language :: Python :: 3 :: Only
Classifier: Programming Language :: Python :: 3.6
Requires-Python: >=3.6
Requires-Dist: Django (<3.0.0,>=2.1.0)
Requires-Dist: pytz (<2020.0,>=2019.0)
Requires-Dist: sqlparse (<1.0.0,>=0.3.0)
Requires-Dist: django-admin-tools (<1.0.0,>=0.8.0)
Requires-Dist: django-fluent-dashboard (<2.0.0,>=1.0.0)
Requires-Dist: django-money (<1.0,>=0.15)
Requires-Dist: django-choices (<2.0.0,>=1.7.0)
Requires-Dist: django-favicon (<1.0.0,>=0.1.3)
Requires-Dist: django-createsuperuserwithpassword (<3.0.0,>=2.0.0)
Requires-Dist: psycopg2 (<3.0.0,>=2.8.0)
Requires-Dist: PyMySQL (<1.0.0,>=0.9.0)
Requires-Dist: django-currentuser (<0.5.0,>=0.4.0)
Requires-Dist: uWSGI (<3.0.0,>=2.0.0)
Requires-Dist: django-getenv (<2.0.0,>=1.3.2)
